scrapy_curl_cffi/__init__.py
scrapy_curl_cffi/adapters.py
scrapy_curl_cffi/handler.py
scrapy_curl_cffi/middlewares.py
scrapy_curl_cffi/utils.py
scrapy_curl_cffi-0.2.0.dist-info/METADATA
scrapy_curl_cffi-0.2.0.dist-info/WHEEL
scrapy_curl_cffi-0.2.0.dist-info/RECORD
