Metadata-Version: 2.4
Name: scrapy-curl-cffi
Version: 0.2.0
Summary: Scrapy integration with curl_cffi (curl-impersonate).
Project-URL: source, https://github.com/divtiply/scrapy-curl-cffi
Author-email: Michel Ace <divtiply@gmail.com>
Requires-Python: >=3.10
Requires-Dist: curl-cffi>=0.11.3
Requires-Dist: scrapy>2.10
Provides-Extra: compression
Requires-Dist: brotli; extra == 'compression'
Requires-Dist: zstandard; extra == 'compression'
